netcup_cli/__init__.py
netcup_cli/main.py
netcup_cli/api/__init__.py
netcup_cli/api/client.py
netcup_cli/api/dns.py
netcup_cli/config/__init__.py
netcup_cli/config/manager.py
netcup_cli/utils/__init__.py
netcup_cli/utils/debug.py
netcup_cli/utils/exceptions.py
netcup_cli/utils/helpers.py
netcup_dns_cli-0.1.2.dist-info/METADATA
netcup_dns_cli-0.1.2.dist-info/WHEEL
netcup_dns_cli-0.1.2.dist-info/entry_points.txt
netcup_dns_cli-0.1.2.dist-info/licenses/LICENSE
netcup_dns_cli-0.1.2.dist-info/RECORD
