Metadata-Version: 2.4
Name: netcup-dns-cli
Version: 0.1.2
Summary: A CLI tool for managing netcup DNS records via the netcup API
Author-email: Daniel Meint <pilots-4-trilogy@icloud.com>
License: MIT
License-File: LICENSE
Keywords: api,cli,dns,domain,nameserver,netcup
Classifier: Development Status :: 4 - Beta
Classifier: Environment :: Console
Classifier: Intended Audience :: Developers
Classifier: Intended Audience :: System Administrators
Classifier: License :: OSI Approved :: MIT License
Classifier: Operating System :: OS Independent
Classifier: Programming Language :: Python :: 3
Classifier: Programming Language :: Python :: 3.8
Classifier: Programming Language :: Python :: 3.9
Classifier: Programming Language :: Python :: 3.10
Classifier: Programming Language :: Python :: 3.11
Classifier: Programming Language :: Python :: 3.12
Classifier: Programming Language :: Python :: 3.13
Classifier: Topic :: Internet :: Name Service (DNS)
Classifier: Topic :: System :: Systems Administration
Classifier: Topic :: Utilities
Requires-Python: >=3.8
Requires-Dist: click>=8.1.0
Requires-Dist: keyring>=24.0.0
Requires-Dist: pydantic>=2.5.0
Requires-Dist: python-dotenv>=1.0.0
Requires-Dist: requests>=2.31.0
Requires-Dist: rich>=13.0.0
Provides-Extra: dev
Requires-Dist: black>=23.0.0; extra == 'dev'
Requires-Dist: mypy>=1.7.0; extra == 'dev'
Requires-Dist: pytest-cov>=4.0.0; extra == 'dev'
Requires-Dist: pytest>=7.0.0; extra == 'dev'
Requires-Dist: ruff>=0.1.0; extra == 'dev'
